bochord/__init__.py
bochord/bochord.py
bochord/cli.py
bochord/epub_dir.py
bochord-1.2.3.dist-info/WHEEL
bochord-1.2.3.dist-info/entry_points.txt
bochord-1.2.3.dist-info/METADATA
bochord-1.2.3.dist-info/RECORD
