Metadata-Version: 2.4
Name: bochord
Version: 1.2.3
Summary: Backup iCloud Books to usable ePubs
Keywords: epub,iCloud,book,backup
Author: AJ Slater
Author-email: AJ Slater <aj@slater.net>
License-Expression: GPL-3.0-only
Classifier: Development Status :: 5 - Production/Stable
Classifier: License :: OSI Approved :: GNU General Public License v3 (GPLv3)
Classifier: Natural Language :: English
Classifier: Operating System :: OS Independent
Classifier: Programming Language :: Python :: 3 :: Only
Requires-Dist: termcolor~=3.0
Requires-Dist: typing-extensions~=4.13
Requires-Python: >=3.10, <4.0
Project-URL: Documentation, https://github.com/ajslater/bochord
Project-URL: Issues, https://github.com/ajslater/issues/
Project-URL: News, https://github.com/ajslater/bochord/blob/main/NEWS.md
Project-URL: Source, https://github.com/ajslater/bochord
